{ 
    "latlng" : [
    {
        "lat": -6.98397,
        "lng": 110.41001
    },
    {
        "lat": -6.98403,
        "lng": 110.41002
    },
    {
        "lat": -6.98415,
        "lng": 110.41002
    },
    {
        "lat": -6.98432,
        "lng": 110.40998
    },
    {
        "lat": -6.9844,
        "lng": 110.40993
    },
    {
        "lat": -6.98455,
        "lng": 110.40988
    },
    {
        "lat": -6.98478,
        "lng": 110.40976
    },
    {
        "lat": -6.98495,
        "lng": 110.40961
    },
    {
        "lat": -6.98562,
        "lng": 110.40923
    },
    {
        "lat": -6.98622,
        "lng": 110.40893
    },
    {
        "lat": -6.98637,
        "lng": 110.40881
    },
    {
        "lat": -6.98656,
        "lng": 110.4087
    },
    {
        "lat": -6.98685,
        "lng": 110.40857
    },
    {
        "lat": -6.98727,
        "lng": 110.40833
    },
    {
        "lat": -6.98766,
        "lng": 110.40815
    },
    {
        "lat": -6.98809,
        "lng": 110.408
    },
    {
        "lat": -6.98847,
        "lng": 110.40783
    },
    {
        "lat": -6.98895,
        "lng": 110.40755
    },
    {
        "lat": -6.98944,
        "lng": 110.40722
    },
    {
        "lat": -6.99113,
        "lng": 110.40629
    },
    {
        "lat": -6.99124,
        "lng": 110.40625
    },
    {
        "lat": -6.99135,
        "lng": 110.40624
    },
    {
        "lat": -6.99182,
        "lng": 110.40631
    },
    {
        "lat": -6.99266,
        "lng": 110.40648
    },
    {
        "lat": -6.99366,
        "lng": 110.40665
    },
    {
        "lat": -6.99402,
        "lng": 110.40671
    },
    {
        "lat": -6.99429,
        "lng": 110.40673
    },
    {
        "lat": -6.99438,
        "lng": 110.40676
    },
    {
        "lat": -6.99451,
        "lng": 110.40685
    },
    {
        "lat": -6.99461,
        "lng": 110.40644
    },
    {
        "lat": -6.99469,
        "lng": 110.40628
    },
    {
        "lat": -6.99491,
        "lng": 110.40605
    },
    {
        "lat": -6.99578,
        "lng": 110.40536
    },
    {
        "lat": -6.99589,
        "lng": 110.4052
    },
    {
        "lat": -6.99597,
        "lng": 110.40499
    },
    {
        "lat": -6.996,
        "lng": 110.4048
    },
    {
        "lat": -6.99604,
        "lng": 110.40361
    },
    {
        "lat": -6.99609,
        "lng": 110.40318
    },
    {
        "lat": -6.99609,
        "lng": 110.40301
    },
    {
        "lat": -6.99606,
        "lng": 110.40278
    },
    {
        "lat": -6.99599,
        "lng": 110.4026
    },
    {
        "lat": -6.99605,
        "lng": 110.40247
    },
    {
        "lat": -6.99613,
        "lng": 110.40234
    },
    {
        "lat": -6.99625,
        "lng": 110.40217
    },
    {
        "lat": -6.99635,
        "lng": 110.40213
    },
    {
        "lat": -6.99705,
        "lng": 110.4019
    },
    {
        "lat": -6.99768,
        "lng": 110.40161
    },
    {
        "lat": -6.99801,
        "lng": 110.40155
    },
    {
        "lat": -6.99857,
        "lng": 110.40154
    },
    {
        "lat": -6.99883,
        "lng": 110.40155
    },
    {
        "lat": -6.99905,
        "lng": 110.40159
    },
    {
        "lat": -6.99918,
        "lng": 110.40164
    },
    {
        "lat": -6.9993,
        "lng": 110.40171
    },
    {
        "lat": -6.99968,
        "lng": 110.40202
    },
    {
        "lat": -6.9998,
        "lng": 110.40214
    },
    {
        "lat": -7.00014,
        "lng": 110.40243
    },
    {
        "lat": -7.00049,
        "lng": 110.40245
    },
    {
        "lat": -7.00078,
        "lng": 110.40238
    },
    {
        "lat": -7.00098,
        "lng": 110.40231
    },
    {
        "lat": -7.00166,
        "lng": 110.40174
    },
    {
        "lat": -7.00241,
        "lng": 110.40122
    },
    {
        "lat": -7.00269,
        "lng": 110.40099
    },
    {
        "lat": -7.00293,
        "lng": 110.40071
    },
    {
        "lat": -7.00311,
        "lng": 110.40038
    },
    {
        "lat": -7.00388,
        "lng": 110.39886
    },
    {
        "lat": -7.00419,
        "lng": 110.39832
    },
    {
        "lat": -7.0045,
        "lng": 110.3977
    },
    {
        "lat": -7.00458,
        "lng": 110.3975
    },
    {
        "lat": -7.0047,
        "lng": 110.39724
    },
    {
        "lat": -7.00485,
        "lng": 110.39702
    },
    {
        "lat": -7.00497,
        "lng": 110.39688
    },
    {
        "lat": -7.00537,
        "lng": 110.39657
    },
    {
        "lat": -7.00567,
        "lng": 110.39641
    },
    {
        "lat": -7.00585,
        "lng": 110.39635
    },
    {
        "lat": -7.00606,
        "lng": 110.3963
    },
    {
        "lat": -7.00629,
        "lng": 110.39627
    },
    {
        "lat": -7.00682,
        "lng": 110.39626
    },
    {
        "lat": -7.00749,
        "lng": 110.39611
    },
    {
        "lat": -7.0077,
        "lng": 110.3961
    },
    {
        "lat": -7.00835,
        "lng": 110.39621
    },
    {
        "lat": -7.00893,
        "lng": 110.39637
    },
    {
        "lat": -7.00895,
        "lng": 110.39645
    },
    {
        "lat": -7.00893,
        "lng": 110.39651
    },
    {
        "lat": -7.00898,
        "lng": 110.39669
    },
    {
        "lat": -7.00935,
        "lng": 110.39769
    },
    {
        "lat": -7.00984,
        "lng": 110.39893
    },
    {
        "lat": -7.00988,
        "lng": 110.39898
    },
    {
        "lat": -7.00993,
        "lng": 110.39902
    },
    {
        "lat": -7.01024,
        "lng": 110.39914
    },
    {
        "lat": -7.01035,
        "lng": 110.39921
    },
    {
        "lat": -7.01081,
        "lng": 110.39954
    },
    {
        "lat": -7.01093,
        "lng": 110.39967
    },
    {
        "lat": -7.01093,
        "lng": 110.39972
    },
    {
        "lat": -7.01088,
        "lng": 110.39979
    },
    {
        "lat": -7.01058,
        "lng": 110.39985
    },
    {
        "lat": -7.01047,
        "lng": 110.39985
    },
    {
        "lat": -7.01036,
        "lng": 110.39984
    },
    {
        "lat": -7.01005,
        "lng": 110.39977
    },
    {
        "lat": -7.00998,
        "lng": 110.39977
    },
    {
        "lat": -7.00991,
        "lng": 110.39978
    },
    {
        "lat": -7.00981,
        "lng": 110.39982
    },
    {
        "lat": -7.00979,
        "lng": 110.39993
    },
    {
        "lat": -7.00992,
        "lng": 110.40046
    },
    {
        "lat": -7.0101,
        "lng": 110.40095
    },
    {
        "lat": -7.0102,
        "lng": 110.40118
    },
    {
        "lat": -7.01038,
        "lng": 110.40148
    },
    {
        "lat": -7.01062,
        "lng": 110.40179
    },
    {
        "lat": -7.01099,
        "lng": 110.40217
    },
    {
        "lat": -7.01107,
        "lng": 110.4022
    },
    {
        "lat": -7.01119,
        "lng": 110.40229
    },
    {
        "lat": -7.01136,
        "lng": 110.40258
    },
    {
        "lat": -7.01163,
        "lng": 110.40344
    },
    {
        "lat": -7.01204,
        "lng": 110.40421
    },
    {
        "lat": -7.01242,
        "lng": 110.40502
    },
    {
        "lat": -7.01265,
        "lng": 110.40544
    },
    {
        "lat": -7.01273,
        "lng": 110.40551
    },
    {
        "lat": -7.0129,
        "lng": 110.40565
    },
    {
        "lat": -7.01299,
        "lng": 110.40569
    },
    {
        "lat": -7.01313,
        "lng": 110.40582
    },
    {
        "lat": -7.01329,
        "lng": 110.40608
    },
    {
        "lat": -7.01347,
        "lng": 110.40643
    },
    {
        "lat": -7.0136,
        "lng": 110.40676
    },
    {
        "lat": -7.01371,
        "lng": 110.40709
    },
    {
        "lat": -7.01401,
        "lng": 110.40812
    },
    {
        "lat": -7.01406,
        "lng": 110.40822
    },
    {
        "lat": -7.01425,
        "lng": 110.40847
    },
    {
        "lat": -7.01427,
        "lng": 110.40864
    },
    {
        "lat": -7.01427,
        "lng": 110.40918
    },
    {
        "lat": -7.01385,
        "lng": 110.4107
    },
    {
        "lat": -7.01385,
        "lng": 110.41092
    },
    {
        "lat": -7.0141,
        "lng": 110.41215
    },
    {
        "lat": -7.01421,
        "lng": 110.41283
    },
    {
        "lat": -7.01393,
        "lng": 110.41284
    },
    {
        "lat": -7.01331,
        "lng": 110.41291
    },
    {
        "lat": -7.01315,
        "lng": 110.41297
    },
    {
        "lat": -7.01301,
        "lng": 110.41309
    },
    {
        "lat": -7.01267,
        "lng": 110.41341
    },
    {
        "lat": -7.0126,
        "lng": 110.41355
    },
    {
        "lat": -7.01236,
        "lng": 110.41437
    },
    {
        "lat": -7.01218,
        "lng": 110.41505
    },
    {
        "lat": -7.01209,
        "lng": 110.4152
    },
    {
        "lat": -7.01197,
        "lng": 110.41534
    },
    {
        "lat": -7.01183,
        "lng": 110.41546
    },
    {
        "lat": -7.01168,
        "lng": 110.41556
    },
    {
        "lat": -7.01156,
        "lng": 110.41561
    },
    {
        "lat": -7.01145,
        "lng": 110.41569
    },
    {
        "lat": -7.01138,
        "lng": 110.41578
    },
    {
        "lat": -7.01127,
        "lng": 110.41572
    },
    {
        "lat": -7.01097,
        "lng": 110.41566
    },
    {
        "lat": -7.01097,
        "lng": 110.41574
    },
    {
        "lat": -7.01114,
        "lng": 110.41576
    },
    {
        "lat": -7.01155,
        "lng": 110.41592
    },
    {
        "lat": -7.01195,
        "lng": 110.41613
    },
    {
        "lat": -7.01222,
        "lng": 110.41631
    },
    {
        "lat": -7.01235,
        "lng": 110.41643
    },
    {
        "lat": -7.01246,
        "lng": 110.4166
    },
    {
        "lat": -7.01264,
        "lng": 110.41698
    },
    {
        "lat": -7.01274,
        "lng": 110.41713
    },
    {
        "lat": -7.01289,
        "lng": 110.41731
    },
    {
        "lat": -7.01312,
        "lng": 110.41752
    },
    {
        "lat": -7.01337,
        "lng": 110.41766
    },
    {
        "lat": -7.01384,
        "lng": 110.41782
    },
    {
        "lat": -7.01558,
        "lng": 110.41831
    },
    {
        "lat": -7.01675,
        "lng": 110.41858
    },
    {
        "lat": -7.01765,
        "lng": 110.41884
    },
    {
        "lat": -7.01957,
        "lng": 110.41936
    },
    {
        "lat": -7.02,
        "lng": 110.41946
    },
    {
        "lat": -7.02117,
        "lng": 110.41981
    },
    {
        "lat": -7.02272,
        "lng": 110.42021
    },
    {
        "lat": -7.02305,
        "lng": 110.42028
    },
    {
        "lat": -7.0237,
        "lng": 110.42046
    },
    {
        "lat": -7.02393,
        "lng": 110.42055
    },
    {
        "lat": -7.02434,
        "lng": 110.42006
    },
    {
        "lat": -7.02492,
        "lng": 110.41962
    },
    {
        "lat": -7.02528,
        "lng": 110.41939
    },
    {
        "lat": -7.02577,
        "lng": 110.41911
    },
    {
        "lat": -7.02599,
        "lng": 110.41902
    },
    {
        "lat": -7.02672,
        "lng": 110.41882
    },
    {
        "lat": -7.02766,
        "lng": 110.41862
    },
    {
        "lat": -7.02792,
        "lng": 110.41862
    },
    {
        "lat": -7.02908,
        "lng": 110.41848
    },
    {
        "lat": -7.02929,
        "lng": 110.41847
    },
    {
        "lat": -7.03019,
        "lng": 110.41835
    },
    {
        "lat": -7.0314,
        "lng": 110.41823
    },
    {
        "lat": -7.03226,
        "lng": 110.41808
    },
    {
        "lat": -7.03313,
        "lng": 110.41793
    },
    {
        "lat": -7.03332,
        "lng": 110.41791
    },
    {
        "lat": -7.03379,
        "lng": 110.41781
    },
    {
        "lat": -7.03438,
        "lng": 110.41762
    },
    {
        "lat": -7.03452,
        "lng": 110.41755
    },
    {
        "lat": -7.03476,
        "lng": 110.41754
    },
    {
        "lat": -7.03498,
        "lng": 110.41762
    },
    {
        "lat": -7.03521,
        "lng": 110.41776
    },
    {
        "lat": -7.03547,
        "lng": 110.41799
    },
    {
        "lat": -7.03556,
        "lng": 110.41813
    },
    {
        "lat": -7.03591,
        "lng": 110.41881
    },
    {
        "lat": -7.03616,
        "lng": 110.41916
    },
    {
        "lat": -7.03675,
        "lng": 110.41971
    },
    {
        "lat": -7.03737,
        "lng": 110.42016
    },
    {
        "lat": -7.03807,
        "lng": 110.42063
    },
    {
        "lat": -7.03846,
        "lng": 110.42085
    },
    {
        "lat": -7.03874,
        "lng": 110.42099
    },
    {
        "lat": -7.03919,
        "lng": 110.42109
    },
    {
        "lat": -7.03977,
        "lng": 110.42117
    },
    {
        "lat": -7.03995,
        "lng": 110.42123
    },
    {
        "lat": -7.04032,
        "lng": 110.42142
    },
    {
        "lat": -7.04081,
        "lng": 110.42195
    },
    {
        "lat": -7.04101,
        "lng": 110.42207
    },
    {
        "lat": -7.04136,
        "lng": 110.4222
    },
    {
        "lat": -7.04146,
        "lng": 110.42221
    },
    {
        "lat": -7.04185,
        "lng": 110.42221
    },
    {
        "lat": -7.0425,
        "lng": 110.42216
    },
    {
        "lat": -7.04304,
        "lng": 110.42204
    },
    {
        "lat": -7.04323,
        "lng": 110.42196
    },
    {
        "lat": -7.044,
        "lng": 110.42158
    },
    {
        "lat": -7.04437,
        "lng": 110.42143
    },
    {
        "lat": -7.04522,
        "lng": 110.42127
    },
    {
        "lat": -7.04561,
        "lng": 110.42121
    },
    {
        "lat": -7.04587,
        "lng": 110.42114
    },
    {
        "lat": -7.04628,
        "lng": 110.421
    },
    {
        "lat": -7.04672,
        "lng": 110.42078
    },
    {
        "lat": -7.04773,
        "lng": 110.42022
    },
    {
        "lat": -7.04783,
        "lng": 110.4202
    },
    {
        "lat": -7.04838,
        "lng": 110.4199
    },
    {
        "lat": -7.04853,
        "lng": 110.41978
    },
    {
        "lat": -7.04946,
        "lng": 110.41922
    },
    {
        "lat": -7.0495,
        "lng": 110.41915
    },
    {
        "lat": -7.05025,
        "lng": 110.41864
    },
    {
        "lat": -7.05142,
        "lng": 110.41765
    },
    {
        "lat": -7.05208,
        "lng": 110.41722
    },
    {
        "lat": -7.05339,
        "lng": 110.41646
    },
    {
        "lat": -7.05405,
        "lng": 110.41612
    },
    {
        "lat": -7.05464,
        "lng": 110.41586
    },
    {
        "lat": -7.05569,
        "lng": 110.41545
    },
    {
        "lat": -7.05884,
        "lng": 110.4144
    },
    {
        "lat": -7.05904,
        "lng": 110.41435
    },
    {
        "lat": -7.05913,
        "lng": 110.41436
    },
    {
        "lat": -7.0606,
        "lng": 110.41386
    },
    {
        "lat": -7.06132,
        "lng": 110.41353
    },
    {
        "lat": -7.0625,
        "lng": 110.41306
    },
    {
        "lat": -7.06381,
        "lng": 110.4126
    },
    {
        "lat": -7.06447,
        "lng": 110.41244
    },
    {
        "lat": -7.06583,
        "lng": 110.41216
    },
    {
        "lat": -7.06949,
        "lng": 110.41155
    },
    {
        "lat": -7.07,
        "lng": 110.41149
    },
    {
        "lat": -7.07021,
        "lng": 110.41144
    },
    {
        "lat": -7.07139,
        "lng": 110.41125
    },
    {
        "lat": -7.07202,
        "lng": 110.41118
    },
    {
        "lat": -7.07244,
        "lng": 110.41118
    },
    {
        "lat": -7.07357,
        "lng": 110.41124
    },
    {
        "lat": -7.07547,
        "lng": 110.4113
    },
    {
        "lat": -7.07627,
        "lng": 110.4113
    },
    {
        "lat": -7.07675,
        "lng": 110.41133
    },
    {
        "lat": -7.0782,
        "lng": 110.41148
    },
    {
        "lat": -7.07858,
        "lng": 110.41148
    },
    {
        "lat": -7.0791,
        "lng": 110.41146
    },
    {
        "lat": -7.08054,
        "lng": 110.41122
    },
    {
        "lat": -7.08124,
        "lng": 110.41108
    },
    {
        "lat": -7.08239,
        "lng": 110.41088
    },
    {
        "lat": -7.0826,
        "lng": 110.41082
    },
    {
        "lat": -7.08311,
        "lng": 110.41065
    },
    {
        "lat": -7.08328,
        "lng": 110.41056
    },
    {
        "lat": -7.08395,
        "lng": 110.41016
    },
    {
        "lat": -7.08479,
        "lng": 110.40959
    },
    {
        "lat": -7.08566,
        "lng": 110.40901
    },
    {
        "lat": -7.08585,
        "lng": 110.40892
    },
    {
        "lat": -7.08634,
        "lng": 110.40877
    },
    {
        "lat": -7.0867,
        "lng": 110.40871
    },
    {
        "lat": -7.08703,
        "lng": 110.40871
    },
    {
        "lat": -7.08774,
        "lng": 110.40876
    },
    {
        "lat": -7.08807,
        "lng": 110.40877
    },
    {
        "lat": -7.08952,
        "lng": 110.40885
    },
    {
        "lat": -7.0909,
        "lng": 110.40887
    },
    {
        "lat": -7.09109,
        "lng": 110.40888
    },
    {
        "lat": -7.09161,
        "lng": 110.40895
    },
    {
        "lat": -7.09206,
        "lng": 110.40907
    },
    {
        "lat": -7.09255,
        "lng": 110.40923
    },
    {
        "lat": -7.0933,
        "lng": 110.40954
    },
    {
        "lat": -7.094,
        "lng": 110.40978
    },
    {
        "lat": -7.09444,
        "lng": 110.40997
    },
    {
        "lat": -7.09485,
        "lng": 110.41008
    },
    {
        "lat": -7.09535,
        "lng": 110.41011
    },
    {
        "lat": -7.09558,
        "lng": 110.4101
    },
    {
        "lat": -7.0963,
        "lng": 110.41004
    },
    {
        "lat": -7.09729,
        "lng": 110.40986
    },
    {
        "lat": -7.09788,
        "lng": 110.4097
    },
    {
        "lat": -7.09923,
        "lng": 110.40937
    },
    {
        "lat": -7.09978,
        "lng": 110.40926
    },
    {
        "lat": -7.10032,
        "lng": 110.40916
    },
    {
        "lat": -7.10091,
        "lng": 110.40909
    },
    {
        "lat": -7.10151,
        "lng": 110.40907
    },
    {
        "lat": -7.10252,
        "lng": 110.40912
    },
    {
        "lat": -7.10266,
        "lng": 110.40914
    },
    {
        "lat": -7.1032,
        "lng": 110.4093
    },
    {
        "lat": -7.10348,
        "lng": 110.40942
    },
    {
        "lat": -7.10373,
        "lng": 110.40958
    },
    {
        "lat": -7.10446,
        "lng": 110.40997
    },
    {
        "lat": -7.10545,
        "lng": 110.41053
    },
    {
        "lat": -7.10627,
        "lng": 110.41092
    },
    {
        "lat": -7.10681,
        "lng": 110.41126
    },
    {
        "lat": -7.1071,
        "lng": 110.41148
    },
    {
        "lat": -7.10768,
        "lng": 110.41199
    },
    {
        "lat": -7.10774,
        "lng": 110.41202
    },
    {
        "lat": -7.10826,
        "lng": 110.41244
    },
    {
        "lat": -7.10862,
        "lng": 110.41263
    },
    {
        "lat": -7.10876,
        "lng": 110.41268
    },
    {
        "lat": -7.10911,
        "lng": 110.41278
    },
    {
        "lat": -7.10929,
        "lng": 110.41282
    },
    {
        "lat": -7.10956,
        "lng": 110.41285
    },
    {
        "lat": -7.11013,
        "lng": 110.41283
    },
    {
        "lat": -7.11044,
        "lng": 110.41278
    },
    {
        "lat": -7.11123,
        "lng": 110.4125
    },
    {
        "lat": -7.11154,
        "lng": 110.41242
    },
    {
        "lat": -7.11183,
        "lng": 110.41239
    },
    {
        "lat": -7.1122,
        "lng": 110.41239
    },
    {
        "lat": -7.11239,
        "lng": 110.41241
    },
    {
        "lat": -7.11265,
        "lng": 110.41247
    },
    {
        "lat": -7.11296,
        "lng": 110.41257
    },
    {
        "lat": -7.11408,
        "lng": 110.41298
    },
    {
        "lat": -7.11519,
        "lng": 110.41323
    },
    {
        "lat": -7.11554,
        "lng": 110.41327
    },
    {
        "lat": -7.11594,
        "lng": 110.41327
    },
    {
        "lat": -7.11628,
        "lng": 110.41322
    },
    {
        "lat": -7.11674,
        "lng": 110.41309
    },
    {
        "lat": -7.11701,
        "lng": 110.41299
    },
    {
        "lat": -7.11759,
        "lng": 110.41273
    },
    {
        "lat": -7.1184,
        "lng": 110.41234
    },
    {
        "lat": -7.11874,
        "lng": 110.41211
    },
    {
        "lat": -7.11901,
        "lng": 110.41184
    },
    {
        "lat": -7.11967,
        "lng": 110.41107
    },
    {
        "lat": -7.12012,
        "lng": 110.41059
    },
    {
        "lat": -7.1208,
        "lng": 110.40998
    },
    {
        "lat": -7.12099,
        "lng": 110.40975
    },
    {
        "lat": -7.12133,
        "lng": 110.40912
    },
    {
        "lat": -7.12159,
        "lng": 110.40861
    },
    {
        "lat": -7.12177,
        "lng": 110.40831
    },
    {
        "lat": -7.12223,
        "lng": 110.40768
    },
    {
        "lat": -7.12286,
        "lng": 110.40707
    },
    {
        "lat": -7.12315,
        "lng": 110.40686
    },
    {
        "lat": -7.12354,
        "lng": 110.40665
    },
    {
        "lat": -7.12399,
        "lng": 110.40651
    },
    {
        "lat": -7.12469,
        "lng": 110.40637
    },
    {
        "lat": -7.12509,
        "lng": 110.40627
    },
    {
        "lat": -7.12534,
        "lng": 110.40615
    },
    {
        "lat": -7.12561,
        "lng": 110.40597
    },
    {
        "lat": -7.12684,
        "lng": 110.40549
    },
    {
        "lat": -7.12714,
        "lng": 110.40545
    },
    {
        "lat": -7.12722,
        "lng": 110.40546
    },
    {
        "lat": -7.12733,
        "lng": 110.4055
    },
    {
        "lat": -7.12757,
        "lng": 110.40566
    },
    {
        "lat": -7.1277,
        "lng": 110.40569
    },
    {
        "lat": -7.1278,
        "lng": 110.4057
    },
    {
        "lat": -7.12808,
        "lng": 110.40569
    },
    {
        "lat": -7.12823,
        "lng": 110.40565
    },
    {
        "lat": -7.1285,
        "lng": 110.40555
    },
    {
        "lat": -7.12878,
        "lng": 110.40541
    },
    {
        "lat": -7.12961,
        "lng": 110.40511
    },
    {
        "lat": -7.12967,
        "lng": 110.40506
    },
    {
        "lat": -7.12979,
        "lng": 110.40473
    },
    {
        "lat": -7.12984,
        "lng": 110.40451
    },
    {
        "lat": -7.12988,
        "lng": 110.40418
    },
    {
        "lat": -7.13137,
        "lng": 110.40393
    },
    {
        "lat": -7.13244,
        "lng": 110.40378
    },
    {
        "lat": -7.13259,
        "lng": 110.40377
    },
    {
        "lat": -7.13292,
        "lng": 110.40379
    },
    {
        "lat": -7.13313,
        "lng": 110.40383
    },
    {
        "lat": -7.13362,
        "lng": 110.40394
    },
    {
        "lat": -7.13483,
        "lng": 110.40429
    },
    {
        "lat": -7.13573,
        "lng": 110.40453
    },
    {
        "lat": -7.13656,
        "lng": 110.40473
    },
    {
        "lat": -7.13689,
        "lng": 110.40482
    },
    {
        "lat": -7.13824,
        "lng": 110.40516
    },
    {
        "lat": -7.13901,
        "lng": 110.40536
    },
    {
        "lat": -7.14039,
        "lng": 110.40565
    },
    {
        "lat": -7.14135,
        "lng": 110.40582
    },
    {
        "lat": -7.1434,
        "lng": 110.40609
    },
    {
        "lat": -7.14368,
        "lng": 110.40615
    },
    {
        "lat": -7.14439,
        "lng": 110.40642
    },
    {
        "lat": -7.14493,
        "lng": 110.40663
    },
    {
        "lat": -7.14521,
        "lng": 110.40676
    },
    {
        "lat": -7.14546,
        "lng": 110.40686
    },
    {
        "lat": -7.14589,
        "lng": 110.40706
    },
    {
        "lat": -7.14723,
        "lng": 110.40766
    },
    {
        "lat": -7.14958,
        "lng": 110.40865
    },
    {
        "lat": -7.15209,
        "lng": 110.40943
    },
    {
        "lat": -7.15417,
        "lng": 110.41029
    },
    {
        "lat": -7.15543,
        "lng": 110.41074
    },
    {
        "lat": -7.15844,
        "lng": 110.41178
    },
    {
        "lat": -7.15914,
        "lng": 110.412
    },
    {
        "lat": -7.16031,
        "lng": 110.41228
    },
    {
        "lat": -7.16187,
        "lng": 110.41259
    },
    {
        "lat": -7.16344,
        "lng": 110.41288
    },
    {
        "lat": -7.16554,
        "lng": 110.41332
    },
    {
        "lat": -7.16689,
        "lng": 110.41358
    },
    {
        "lat": -7.1677,
        "lng": 110.41381
    },
    {
        "lat": -7.16874,
        "lng": 110.41419
    },
    {
        "lat": -7.1693,
        "lng": 110.41445
    },
    {
        "lat": -7.17063,
        "lng": 110.41512
    },
    {
        "lat": -7.17178,
        "lng": 110.41567
    },
    {
        "lat": -7.17284,
        "lng": 110.41622
    },
    {
        "lat": -7.17317,
        "lng": 110.41637
    },
    {
        "lat": -7.17362,
        "lng": 110.41654
    },
    {
        "lat": -7.17387,
        "lng": 110.41668
    },
    {
        "lat": -7.17411,
        "lng": 110.41686
    },
    {
        "lat": -7.17432,
        "lng": 110.41693
    },
    {
        "lat": -7.17445,
        "lng": 110.41694
    },
    {
        "lat": -7.17472,
        "lng": 110.41689
    },
    {
        "lat": -7.17489,
        "lng": 110.41687
    },
    {
        "lat": -7.17507,
        "lng": 110.41689
    },
    {
        "lat": -7.17525,
        "lng": 110.41694
    },
    {
        "lat": -7.17554,
        "lng": 110.41705
    },
    {
        "lat": -7.17582,
        "lng": 110.41723
    },
    {
        "lat": -7.17608,
        "lng": 110.41745
    },
    {
        "lat": -7.17632,
        "lng": 110.41768
    },
    {
        "lat": -7.17679,
        "lng": 110.41821
    },
    {
        "lat": -7.17723,
        "lng": 110.41873
    },
    {
        "lat": -7.17784,
        "lng": 110.41968
    },
    {
        "lat": -7.17852,
        "lng": 110.42081
    },
    {
        "lat": -7.17914,
        "lng": 110.42173
    },
    {
        "lat": -7.17938,
        "lng": 110.42217
    },
    {
        "lat": -7.17951,
        "lng": 110.42248
    },
    {
        "lat": -7.17963,
        "lng": 110.42272
    },
    {
        "lat": -7.17974,
        "lng": 110.4229
    },
    {
        "lat": -7.17991,
        "lng": 110.42309
    },
    {
        "lat": -7.18008,
        "lng": 110.42322
    },
    {
        "lat": -7.18046,
        "lng": 110.42343
    },
    {
        "lat": -7.18058,
        "lng": 110.42352
    },
    {
        "lat": -7.18173,
        "lng": 110.42457
    },
    {
        "lat": -7.18226,
        "lng": 110.42501
    },
    {
        "lat": -7.18297,
        "lng": 110.42559
    },
    {
        "lat": -7.18403,
        "lng": 110.42638
    },
    {
        "lat": -7.18522,
        "lng": 110.42718
    },
    {
        "lat": -7.18542,
        "lng": 110.42728
    },
    {
        "lat": -7.18582,
        "lng": 110.4274
    },
    {
        "lat": -7.18609,
        "lng": 110.42742
    },
    {
        "lat": -7.18643,
        "lng": 110.4274
    },
    {
        "lat": -7.18713,
        "lng": 110.42733
    },
    {
        "lat": -7.1875,
        "lng": 110.42723
    },
    {
        "lat": -7.18779,
        "lng": 110.42711
    },
    {
        "lat": -7.18851,
        "lng": 110.42668
    },
    {
        "lat": -7.18903,
        "lng": 110.42631
    },
    {
        "lat": -7.18979,
        "lng": 110.42581
    },
    {
        "lat": -7.19,
        "lng": 110.42573
    },
    {
        "lat": -7.1902,
        "lng": 110.42569
    },
    {
        "lat": -7.1907,
        "lng": 110.42563
    },
    {
        "lat": -7.1913,
        "lng": 110.42566
    },
    {
        "lat": -7.19408,
        "lng": 110.42601
    },
    {
        "lat": -7.19442,
        "lng": 110.42601
    },
    {
        "lat": -7.19478,
        "lng": 110.42598
    },
    {
        "lat": -7.19505,
        "lng": 110.42594
    },
    {
        "lat": -7.19539,
        "lng": 110.42587
    },
    {
        "lat": -7.19556,
        "lng": 110.42582
    },
    {
        "lat": -7.19597,
        "lng": 110.42567
    },
    {
        "lat": -7.19673,
        "lng": 110.42532
    },
    {
        "lat": -7.19728,
        "lng": 110.42505
    },
    {
        "lat": -7.19744,
        "lng": 110.42495
    },
    {
        "lat": -7.19794,
        "lng": 110.42459
    },
    {
        "lat": -7.19874,
        "lng": 110.42395
    },
    {
        "lat": -7.19902,
        "lng": 110.42375
    },
    {
        "lat": -7.1993,
        "lng": 110.42362
    },
    {
        "lat": -7.19978,
        "lng": 110.42348
    },
    {
        "lat": -7.20056,
        "lng": 110.4233
    },
    {
        "lat": -7.2008,
        "lng": 110.42327
    },
    {
        "lat": -7.20118,
        "lng": 110.42326
    },
    {
        "lat": -7.20359,
        "lng": 110.42347
    },
    {
        "lat": -7.20554,
        "lng": 110.42378
    },
    {
        "lat": -7.2065,
        "lng": 110.42396
    },
    {
        "lat": -7.20735,
        "lng": 110.42405
    },
    {
        "lat": -7.20794,
        "lng": 110.42408
    },
    {
        "lat": -7.20835,
        "lng": 110.42413
    },
    {
        "lat": -7.209,
        "lng": 110.42428
    },
    {
        "lat": -7.20946,
        "lng": 110.42441
    },
    {
        "lat": -7.21004,
        "lng": 110.42456
    },
    {
        "lat": -7.2103,
        "lng": 110.4246
    },
    {
        "lat": -7.21055,
        "lng": 110.42463
    },
    {
        "lat": -7.2119,
        "lng": 110.42464
    },
    {
        "lat": -7.21211,
        "lng": 110.42467
    },
    {
        "lat": -7.21236,
        "lng": 110.42472
    },
    {
        "lat": -7.21263,
        "lng": 110.42475
    },
    {
        "lat": -7.21285,
        "lng": 110.4248
    },
    {
        "lat": -7.21309,
        "lng": 110.42489
    },
    {
        "lat": -7.21336,
        "lng": 110.42502
    },
    {
        "lat": -7.21357,
        "lng": 110.42515
    },
    {
        "lat": -7.21414,
        "lng": 110.42557
    },
    {
        "lat": -7.21496,
        "lng": 110.42624
    },
    {
        "lat": -7.21568,
        "lng": 110.42688
    },
    {
        "lat": -7.21598,
        "lng": 110.4272
    },
    {
        "lat": -7.21647,
        "lng": 110.42779
    },
    {
        "lat": -7.21708,
        "lng": 110.42857
    },
    {
        "lat": -7.21748,
        "lng": 110.42905
    },
    {
        "lat": -7.21761,
        "lng": 110.42917
    },
    {
        "lat": -7.2179,
        "lng": 110.42939
    },
    {
        "lat": -7.21899,
        "lng": 110.43012
    },
    {
        "lat": -7.21976,
        "lng": 110.43054
    },
    {
        "lat": -7.22019,
        "lng": 110.43075
    },
    {
        "lat": -7.22089,
        "lng": 110.43092
    },
    {
        "lat": -7.22122,
        "lng": 110.43098
    },
    {
        "lat": -7.22178,
        "lng": 110.43106
    },
    {
        "lat": -7.22391,
        "lng": 110.43129
    },
    {
        "lat": -7.22455,
        "lng": 110.43131
    },
    {
        "lat": -7.22491,
        "lng": 110.43128
    },
    {
        "lat": -7.2252,
        "lng": 110.43122
    },
    {
        "lat": -7.22624,
        "lng": 110.43099
    },
    {
        "lat": -7.22995,
        "lng": 110.43023
    },
    {
        "lat": -7.2304,
        "lng": 110.43016
    },
    {
        "lat": -7.23204,
        "lng": 110.42996
    },
    {
        "lat": -7.23268,
        "lng": 110.42994
    },
    {
        "lat": -7.23313,
        "lng": 110.42996
    },
    {
        "lat": -7.23338,
        "lng": 110.42999
    },
    {
        "lat": -7.23468,
        "lng": 110.43021
    },
    {
        "lat": -7.23491,
        "lng": 110.43026
    },
    {
        "lat": -7.23513,
        "lng": 110.43033
    },
    {
        "lat": -7.23538,
        "lng": 110.43045
    },
    {
        "lat": -7.23558,
        "lng": 110.43058
    },
    {
        "lat": -7.23576,
        "lng": 110.43073
    },
    {
        "lat": -7.23621,
        "lng": 110.43116
    },
    {
        "lat": -7.23656,
        "lng": 110.43157
    },
    {
        "lat": -7.23686,
        "lng": 110.43199
    },
    {
        "lat": -7.23746,
        "lng": 110.43304
    },
    {
        "lat": -7.23771,
        "lng": 110.4334
    },
    {
        "lat": -7.23797,
        "lng": 110.43373
    },
    {
        "lat": -7.23817,
        "lng": 110.43396
    },
    {
        "lat": -7.23837,
        "lng": 110.43416
    },
    {
        "lat": -7.23863,
        "lng": 110.43437
    },
    {
        "lat": -7.23909,
        "lng": 110.43467
    },
    {
        "lat": -7.23931,
        "lng": 110.43479
    },
    {
        "lat": -7.23958,
        "lng": 110.43491
    },
    {
        "lat": -7.23985,
        "lng": 110.43499
    },
    {
        "lat": -7.2404,
        "lng": 110.4351
    },
    {
        "lat": -7.24067,
        "lng": 110.43513
    },
    {
        "lat": -7.24123,
        "lng": 110.43515
    },
    {
        "lat": -7.24152,
        "lng": 110.43512
    },
    {
        "lat": -7.242,
        "lng": 110.43505
    },
    {
        "lat": -7.24358,
        "lng": 110.43473
    },
    {
        "lat": -7.24387,
        "lng": 110.43451
    },
    {
        "lat": -7.24398,
        "lng": 110.4344
    },
    {
        "lat": -7.24415,
        "lng": 110.43417
    },
    {
        "lat": -7.2453,
        "lng": 110.43247
    },
    {
        "lat": -7.24576,
        "lng": 110.43286
    },
    {
        "lat": -7.24583,
        "lng": 110.43294
    },
    {
        "lat": -7.24592,
        "lng": 110.43307
    },
    {
        "lat": -7.24605,
        "lng": 110.43333
    },
    {
        "lat": -7.24562,
        "lng": 110.43364
    }
],
    "shelter" : [
    {
        "bs_id": 1,
        "bs_lat": "-6.98407995",
        "bs_lng": "110.40956676546713",
        "bs_nm": "Tugu Muda",
        "addr": "Tugu Muda, Sekayu, Semarang Tengah, Semarang, Jawa Tengah, Jawa, Indonesia",
        "enc": "a5635e1f4428a9c4fb1c6c62c2dfb95c",
        "bs_stop": "1"
    },
    {
        "bs_id": 2,
        "bs_lat": "-7.008352501602003",
        "bs_lng": "110.39619680726902",
        "bs_nm": "Taman Sampangan",
        "addr": "Jalan Kelud Raya, RW 04, Bendan Ngisor, Gajah Mungkur, Semarang, Jawa Tengah, Jawa, 50233, Indonesia",
        "enc": "979bbdd320655af65b71031ea017c666",
        "bs_stop": "1"
    },
    {
        "bs_id": 3,
        "bs_lat": "-7.032260844265417",
        "bs_lng": "110.41813834570351",
        "bs_nm": "Kelurahan Ngesrep",
        "addr": "Jalan Setia Budi, RW 01, Ngesrep, Banyumanik, Semarang, Jawa Tengah, Jawa, 50254, Indonesia",
        "enc": "3b390cb0c45e2d658947134a08b494e9",
        "bs_stop": "1"
    },
    {
        "bs_id": 4,
        "bs_lat": "-7.055705306359979",
        "bs_lng": "110.4155119811185",
        "bs_nm": "Srondol Kulon",
        "addr": "Jalan Setia Budi, RW 06, Srondol Kulon, Banyumanik, Semarang, Jawa Tengah, Jawa, 50259, Indonesia",
        "enc": "4fa4eb73f7f114fc66413a3ba1f65e27",
        "bs_stop": "1"
    },
    {
        "bs_id": 5,
        "bs_lat": "-7.134800457824791",
        "bs_lng": "110.40439143776895",
        "bs_nm": "SMA 1 Ungaran",
        "addr": "Jalan Diponegoro, Dliwang, Ungaran, Semarang, Jawa Tengah, Jawa, 50511, Indonesia",
        "enc": "68c332852b069108debec9ff478b5b7b",
        "bs_stop": "1"
    },
    {
        "bs_id": 6,
        "bs_lat": "-7.24546695",
        "bs_lng": "110.43343835403695",
        "bs_nm": "Terminal Bawen",
        "addr": "Terminal Bawen, 20, Ngempla, Tegalrejo, Semarang, Jawa Tengah, Jawa, 13245, Indonesia",
        "enc": "3e961533ddc9c23fd68eaa04fa6a7df8",
        "bs_stop": "1"
    }
]
}